RasediPaymentSDK.py
test.py
test_import.py
rasedi_payment_sdk/__init__.py
rasedi_payment_sdk/auth.py
rasedi_payment_sdk/client.py
rasedi_payment_sdk/constant.py
rasedi_payment_sdk/enum.py
rasedi_payment_sdk/interface.py
rasedi_payment_sdk-1.0.6.dist-info/licenses/LICENSE
rasedi_payment_sdk-1.0.6.dist-info/METADATA
rasedi_payment_sdk-1.0.6.dist-info/WHEEL
rasedi_payment_sdk-1.0.6.dist-info/top_level.txt
rasedi_payment_sdk-1.0.6.dist-info/RECORD
