Metadata-Version: 2.4
Name: rasedi_payment_sdk
Version: 1.0.6
Summary: Official Python SDK for the Rasedi API
Requires-Python: >=3.0
License-File: LICENSE
Requires-Dist: httpx
Requires-Dist: typing
Requires-Dist: cryptography
Dynamic: license-file
